{
  "source_site": "SarkariResult",
  "source_url": "https://www.sarkariresult.com/answerkey/",
  "category": "government_jobs",
  "scraped_at": "2026-07-16T07:00:09.782641Z",
  "title": "AIBE 21 Final Answer Key 2026",
  "link": "https://www.sarkariresult.com/2026/all-india-bar-aibe-21/",
  "date": null,
  "description": null,
  "raw_text": "AIBE 21 Final Answer Key 2026",
  "all_links": [
    {
      "text": "AIBE 21 Final Answer Key 2026",
      "url": "https://www.sarkariresult.com/2026/all-india-bar-aibe-21/"
    }
  ],
  "all_images": [],
  "full_title": "All India Bar Examination AIBE 21th Final Answer Key",
  "full_text": "Telegram\nWhatsApp\nInstagram\nFrequently Asked Questions",
  "tables": [
    [
      [
        "Name Of Post :",
        "All India Bar Examination AIBE 21th Final Answer Key"
      ],
      [
        "Post Date / Update :",
        "10 July 2026 | 08:59 PM"
      ],
      [
        "Short Information",
        "All India Bar Examination AIBE AIBE XXI has released the online application for AIBE XXI 2026 will start from 11 February 2026 and the last date to apply will be 30 April 2026.candidates should read the AIBE XXI 2026 information brochure for all the information related to the AIBE exam like syllabus, eligibility, age limit, fees, information and other types of information and then apply."
      ]
    ],
    [
      [
        "Bar Council of India (BCI) All India Bar Examination AIBE AIBE XXI Examination 2026 AIBE 21th Exam 2026 : Short Details of Notification WWW.SARKARIRESULT.COM"
      ],
      [
        "Important Dates Application Begin : 11/02/2026 Last Date for Apply Online : 30/04/2026 Fee Payment Last Date : 01/05/2026 Correction Last Date : 03/05/2026 AIBE XIX Exam Date : 07/06/2026 Admit Card Available : 22/05/2026 Final Answer Key Available : 10/07/2026 Result Declared : Notified Soon",
        "Application Fee General (UR) / OBC : 3500 /- SC / ST : 2500/- Pay the Examination Fee Through E Challan Offline Mode or Pay the Exam Fee Through Online Debit Card, Credit Card or Net Banking Fee Mode"
      ],
      [
        "All India Bar Exam AIBE XXI Notification 2026 : Age Limit Details No Age Limit in All India Bar Exam AIBE AIBE XXI 2026"
      ],
      [
        "Bar Council AIBE 21 Exam 2026 : Eligibility Details"
      ],
      [
        "Exam Name",
        "AIBE Eligibility 2026"
      ],
      [
        "All India Bar Examination AIBE XXI",
        "Bachelor Degree in Law (LLB) in Any Recognized Board in India. General and OBC Candidate : 45% SC / ST / PH : 40% More Eligibility Details Read the Notification"
      ],
      [
        "AIBE AIBE XXI Exam 2026: Document Required List Class 10th Matriculation Certificate 10+2 Intermediate/Diploma Certificate Law Degree LLB 3 Years/LLB 5 Years Certificate Passport Size Photograph Signature photograph Enrollment Certificate Category Certificate Disability Certificate All documents have to be uploaded in PDF format whose size should be less than 1 MB."
      ],
      [
        "Interested Candidates Can Read the AIBE 21th Exam 2026  Full Notification Before Apply Online"
      ],
      [
        "Download Sarkari Result New Mobile Apps"
      ],
      [
        "Android Apps",
        "Apple IOS Apps"
      ],
      [
        "Some Useful Important Links"
      ],
      [
        "Download Final Answer Key",
        "Click Here"
      ],
      [
        "Download Admit Card",
        "Click Here"
      ],
      [
        "Apply Online",
        "Registration | Login"
      ],
      [
        "How to Fill Form (Video Hindi)",
        "Version I | Version II"
      ],
      [
        "Download AIBE 21 Notice",
        "Click Here"
      ],
      [
        "Download Syllabus",
        "AIBE Syllabus"
      ],
      [
        "Photo to PDF, Remove Background, PDF Compress, Image Resizer, JPG to PDF and Other Tools",
        "Click Here"
      ],
      [
        "Join Sarkari Result Channel",
        "Telegram | WhatsApp"
      ],
      [
        "Official Website",
        "All India Bar Exam Official Website"
      ]
    ]
  ],
  "important_dates": null,
  "important_links": [
    {
      "text": "Join Us",
      "url": "https://t.me/SarkariResult2012"
    },
    {
      "text": "Follow",
      "url": "https://www.instagram.com/sarkariresult.comofficial"
    },
    {
      "text": "WWW.SARKARIRESULT.COM",
      "url": "https://www.sarkariresult.com/"
    },
    {
      "text": "Apple IOS Apps",
      "url": "https://itunes.apple.com/us/app/sarkari-result/id1051363935?ls=1&mt=8"
    },
    {
      "text": "Click Here",
      "url": "https://www.allindiabarexamination.com/img/Final%20Answer%20Key_AIBE%20XXI.pdf"
    },
    {
      "text": "Click Here",
      "url": "https://aibe.digivarsity.online/WebApp/Forms/UserAuthentication.aspx"
    },
    {
      "text": "Registration",
      "url": "https://aibe.digivarsity.online/WebApp/Forms/Authentication.aspx"
    },
    {
      "text": "Click Here",
      "url": "https://www.allindiabarexamination.com/img/BCIT-D-0014-2026%20-%20Schedule%20for%20All%20India%20BarExam-XXI.pdf"
    },
    {
      "text": "AIBE Syllabus",
      "url": "https://doc.sarkariresults.org.in/AIBE-XX%20Syllabus.pdf"
    },
    {
      "text": "Click Here",
      "url": "https://sarkariresult.tools/"
    },
    {
      "text": "All India Bar Exam Official Website",
      "url": "https://www.allindiabarexamination.com/"
    }
  ],
  "fetch_error": null,
  "site_name": "SarkariResult",
  "category_label": "Answer Key",
  "scraped_date": "2026-07-16"
}