{
  "title": "AAI Manager, Junior Executive Recruitment 2026 + Government Job + India + Apply by 07/09/2026",
  "slug": "aai-manager-junior-executive-recruitment-2026",
  "excerpt": "Apply for AAI Manager, Junior Executive Recruitment 2026. 389 posts available. Last date to apply: 07/09/2026. Check eligibility and application process.",
  "value_prop": "_Apply for AAI Manager, Junior Executive Recruitment 2026 to start your career in the government sector_",
  "secondary_subtitle": "_Get a chance to work with Airports Authority of India and secure your future_",
  "content": "<i>Apply for AAI Manager, Junior Executive Recruitment 2026 to start your career in the government sector</i><br><i>Get a chance to work with Airports Authority of India and secure your future</i><br><br><h2>Quick Highlights</h2><table><tr><td>Programme Name</td><td>AAI Manager, Junior Executive Recruitment 2026</td></tr><tr><td>Organization</td><td><strong>Airports Authority of India (AAI)</strong></td></tr><tr><td>Opportunity Type</td><td>Government Job</td></tr><tr><td>Funding Type</td><td>As per official notification</td></tr><tr><td>Eligible Applicants</td><td>Indian citizens</td></tr><tr><td>Country</td><td><strong>India</strong></td></tr><tr><td>Duration</td><td>As per official notification</td></tr><tr><td>Deadline</td><td><strong>07/09/2026</strong></td></tr><tr><td>Status</td><td>Open</td></tr></table><br><h2>Opportunity Overview</h2><table><tr><td>Host Organization</td><td><strong>Airports Authority of India (AAI)</strong></td></tr><tr><td>Programme</td><td>AAI Manager, Junior Executive Recruitment 2026</td></tr><tr><td>Programme Type</td><td>Government Job</td></tr><tr><td>Funding Category</td><td>As per official notification</td></tr><tr><td>Eligible Applicants</td><td>Indian citizens</td></tr><tr><td>Location</td><td><strong>India</strong></td></tr><tr><td>Application Mode</td><td>Online</td></tr></table><br><h2>About Organization</h2><p>Airports Authority of India (AAI) is a government organization responsible for managing and maintaining airports in India.</p><p>AAI works under the Ministry of Civil Aviation and is headquartered in New Delhi.</p><br><h2>About the Programme</h2><p>The AAI Manager, Junior Executive Recruitment 2026 is a government job opportunity for Indian citizens.</p><p>The programme aims to recruit eligible candidates for various posts in AAI, including Manager and Junior Executive positions.</p><br><h2>Benefits</h2><table><tr><td>Tuition</td><td>As per official notification</td></tr><tr><td>Stipend</td><td>As per official notification</td></tr><tr><td>Accommodation</td><td>As per official notification</td></tr><tr><td>Airfare</td><td>As per official notification</td></tr><tr><td>Mentorship</td><td>As per official notification</td></tr><tr><td>Networking</td><td>Opportunities to network with professionals in the field</td></tr><tr><td>Certification</td><td>As per official notification</td></tr><tr><td>Other Benefits</td><td>As per official notification</td></tr></table><br><h2>Programme Objectives / Key Features</h2><table><tr><td>Objective</td><td>To recruit eligible candidates for various posts in AAI</td></tr><tr><td>Status/Details</td><td>Open for application</td></tr></table><br><h2>Eligibility Criteria</h2><table><tr><td>Nationality</td><td>Indian</td></tr><tr><td>Degree</td><td>As per official notification</td></tr><tr><td>Experience</td><td>As per official notification</td></tr><tr><td>Age</td><td>As per official notification</td></tr><tr><td>Language</td><td>As per official notification</td></tr><tr><td>Other Requirements</td><td>As per official notification</td></tr></table><br><h2>Eligible Fields / Eligible Applicants</h2><table><tr><td>Post Name</td><td>Eligible Applicants</td></tr><tr><td>Junior Executive (Finance)</td><td>MBA with Finance / PG Diploma in Management with Specialization in Finance OR CA / CFA</td></tr><tr><td>Junior Executive (Law)</td><td>Bachelor Degree in Law (3 year / 5 Year) From Any Recognized University in India. Enrolled with Bar Council in India.</td></tr></table><br><h2>Required Documents</h2><table><tr><td>Document</td><td>Required</td></tr><tr><td>Photo</td><td>Yes</td></tr><tr><td>Signature</td><td>Yes</td></tr><tr><td>ID Proof</td><td>Yes</td></tr><tr><td>Address Proof</td><td>Yes</td></tr></table><br><h2>Programme Timeline</h2><table><tr><td>Event</td><td>Date</td></tr><tr><td>Application Start Date</td><td>08/08/2026</td></tr><tr><td>Application End Date</td><td>07/09/2026</td></tr><tr><td>Exam Date</td><td>As per Schedule</td></tr></table><br><h2>How to Apply</h2><table><tr><td>Step</td><td>Action</td></tr><tr><td>1</td><td>Read the official notification carefully</td></tr><tr><td>2</td><td>Check the eligibility criteria</td></tr><tr><td>3</td><td>Fill the online application form</td></tr><tr><td>4</td><td>Upload the required documents</td></tr><tr><td>5</td><td>Submit the application form</td></tr></table><br><h2>Important Links</h2><table><tr><td>Description</td><td>Official Link</td></tr><tr><td>Apply Online</td><td>https://www.aai.aero/en</td></tr><tr><td>Download Notification</td><td>https://www.aai.aero/sites/default/files/examdashboard_advertisement/Detailed%20Advertisement%2012-2026-CHQ.pdf</td></tr></table><br><h2>FAQs</h2><table><tr><td>Question</td><td>Answer</td></tr><tr><td>What is the last date to apply online?</td><td>07/09/2026</td></tr><tr><td>What is the exam date?</td><td>As per Schedule</td></tr></table><br><h2>CareerFlora Expert Insight</h2><p>The AAI Manager, Junior Executive Recruitment 2026 is a great opportunity for Indian citizens to start their career in the government sector.</p><p>The programme offers a chance to work with Airports Authority of India and secure a future in the field.</p><br><h2>Best Opportunity For</h2><table><tr><td>Category</td><td>Suitable</td></tr><tr><td>Government Job Seekers</td><td>Yes</td></tr><tr><td>Indian Citizens</td><td>Yes</td></tr></table><br><h2>Competition Level</h2><table><tr><td>Category</td><td>Level</td></tr><tr><td>Government Jobs</td><td>High</td></tr></table><br><h2>CareerFlora Recommendation</h2><table><tr><td>Recommendation Area</td><td>Details</td></tr><tr><td>Overall Rating</td><td>4/5</td></tr><tr><td>Funding Opportunity</td><td>As per official notification</td></tr><tr><td>Learning Value</td><td>High</td></tr><tr><td>Career Growth</td><td>High</td></tr><tr><td>Networking</td><td>Opportunities to network with professionals in the field</td></tr><tr><td>Apply Early</td><td>Yes</td></tr></table>",
  "meta_title": "AAI Manager, Junior Executive Recruitment 2026",
  "meta_description": "Apply for AAI Manager, Junior Executive Recruitment 2026. 389 posts available. Last date to apply: 07/09/2026. Check eligibility and application process.",
  "focus_keyword": "AAI Manager, Junior Executive Recruitment 2026",
  "seo_keywords": "government jobs, AAI recruitment, junior executive, manager, India jobs",
  "schema_type": "JobPosting",
  "deadline": "2026-09-07",
  "image_alt": "AAI Manager, Junior Executive Recruitment 2026",
  "tg_caption": "Apply for AAI Manager, Junior Executive Recruitment 2026. 389 posts available. Last date to apply: 07/09/2026. Check eligibility and application process. Read Full Details Below",
  "wa_caption": "AAI Manager, Junior Executive Recruitment 2026. Apply by 07/09/2026",
  "ig_caption": "Apply for AAI Manager, Junior Executive Recruitment 2026 #AAIRecruitment #GovernmentJobs #IndiaJobs",
  "category_id": 1,
  "source_url": "https://www.sarkariresult.com/2026/aai-manager-junior-executive-july26/",
  "source_site": "SarkariResult"
}