{
  "source_site": "SarkariResult",
  "source_url": "https://www.sarkariresult.com/result/",
  "category": "government_jobs",
  "scraped_at": "2026-07-22T20:48:30.745609Z",
  "title": "UPSSSC Stenographer 2024 Result",
  "link": "https://www.sarkariresult.com/upsssc/upsssc-steno-13-exam-2024/",
  "date": null,
  "description": null,
  "raw_text": "UPSSSC Stenographer 2024 Result",
  "all_links": [
    {
      "text": "UPSSSC Stenographer 2024 Result",
      "url": "https://www.sarkariresult.com/upsssc/upsssc-steno-13-exam-2024/"
    }
  ],
  "all_images": [],
  "full_title": "UPSSSC Stenographer Recruitment 2024  Result 2026 for 661 Post",
  "full_text": "Telegram\nWhatsApp\nInstagram\nFrequently Asked Questions",
  "tables": [
    [
      [
        "Name Of Post :",
        "UPSSSC Stenographer Recruitment 2024  Result 2026 for 661 Post"
      ],
      [
        "Post Date / Update :",
        "22 July 2026 | 10:12 PM"
      ],
      [
        "Short Information",
        "Uttar Pradesh Subordinate Service Selection Commission (UPSSSC) Uttar Pradesh Advertisement No.13-Exam/2024, Advertisement of Stenographer Main Examination Recruitment Notification. Those candidates who are interested in this UPSSSC 10+2 Steno Vacancy 2024 can apply online from 26 December 2024 to 25 January 2025. Read the notification for recruitment eligibility, post information, selection procedure, Department Wise Vacancy, pay scale and all other information."
      ]
    ],
    [
      [
        "Uttar Pradesh Subordinate Service Selection Commission (UPSSSC) Uttar Pradesh UPSSSC Stenographer Recruitment 2024 Mains Exam UPSSSC Steno Advt No. : 13-Exam/2024 Short Details of Notification WWW.SARKARIRESULT.COM"
      ],
      [
        "Important Dates Application Begin : 26/12/2024 Last Date for Registration : 25/01/2025 Fee Payment Last Date : 25/01/2025 Correction Last Date : 01/02/2025 Exam Date : 20/01/2026 Admit Card Available : Before Exam Answer Key Available : 22/01/2026 Revised Answer Key Available : 01/04/2026 Result Available : 22/07/2026",
        "Application Fee General / OBC / EWS : 25/- SC / ST : 25/- PH (Dviyang) : 25/- Pay the Examination Fee Through State Bank of India SBI I Collect Fee Mode or Pay the Exam Fee Through E Challan"
      ],
      [
        "UPSSSC Stenographer Notification 2024 : Age Limit as on 01/07/2024 Minimum Age : 18 Years Maximum Age : 40 Years Age Relaxation Extra as per UPSSSC UP  Advertisement No.-13-Exam/2024, Stenographer Main Examination 2024"
      ],
      [
        "UPSSSC Stenographer Recruitment 2024 : Vacancy Details Total : 661 Post"
      ],
      [
        "Post Name",
        "Total Post",
        "UPSSSC Stenographer Eligibility"
      ],
      [
        "Stenographer",
        "661",
        "UPSSSC PET 2023 Score Card. 10+2 Intermediate Exam Passed Hindi Stenographer 80 WPM, Hindi Typing 25 WPM NIELIT CCC Exam Passed More Details Read the Notification."
      ],
      [
        "UPSSSC Stenographer Exam 2024 : Category Wise Vacancy Details"
      ],
      [
        "Post Name",
        "General",
        "EWS",
        "OBC",
        "SC",
        "ST",
        "Total"
      ],
      [
        "Stenographer Advt No 13-Exam/2024",
        "321",
        "46",
        "125",
        "155",
        "14",
        "661"
      ],
      [
        "How to Fill : UPSSSC Stenographer Recruitment Online Form 2024 There are 02 types to apply online for UPSSSC Stenographer Recruitment Advt No. 13-Exam/2024 Recruitment 2024. First: In this, the candidate will have to login with his personal information, the information that has to be given is: PET Registration Number, Date of Birth, Gender, Domicile and Category. Second : In this, the candidate will have to login through his OTP, the information that has to be given is: UPSSSC PET 2023 Registration Number and OTP Password. After login, the complete information of the candidate, his photo and signature will also be visible, the candidate will have to fill the information related to the post he is asking for and the application fee: Rs.25/- will have to be paid. Kindly Check and Collect the All Document – Eligibility, ID Proof, Address Details, Basic Details. Kindly Ready Scan Document Related to Recruitment Form – Photo, Sign, ID Proof, Etc. Before Apply Online / Submit Application Form Must Check the Preview and All Column Carefully. Take A Print Out of Final Submitted Form."
      ],
      [
        "Interested Candidates Can Read the Full UPSSSC Advt No : 13-Exam/2024 Notification Before Apply Online"
      ],
      [
        "Download SarkariResult.Com Official Mobile Apps"
      ],
      [
        "Android Apps",
        "Apple IOS Apps"
      ],
      [
        "Some Useful Important Links"
      ],
      [
        "Download Result",
        "Result | Notice"
      ],
      [
        "Download Revised Answer Key",
        "Click Here"
      ],
      [
        "Download Answer Key",
        "Click Here"
      ],
      [
        "Download Admit Card",
        "Click Here"
      ],
      [
        "Apply Online",
        "Click Here"
      ],
      [
        "Download Notification",
        "Click Here"
      ],
      [
        "Find More UPSSSC Latest Vacancy Through PET 2023",
        "Click Here"
      ],
      [
        "Resume CV Maker, Image Resizer, JPG to PDF Converter, Typing Test Practice, More",
        "Sarkari Tools"
      ],
      [
        "Join Sarkari Result Channel",
        "Telegram | WhatsApp"
      ],
      [
        "Official Website",
        "UPSSSC Official Website"
      ]
    ]
  ],
  "important_dates": null,
  "important_links": [
    {
      "text": "Join Us",
      "url": "https://t.me/SarkariResult2012"
    },
    {
      "text": "Follow",
      "url": "https://www.instagram.com/sarkariresult.comofficial"
    },
    {
      "text": "WWW.SARKARIRESULT.COM",
      "url": "https://www.sarkariresult.com/"
    },
    {
      "text": "Apple IOS Apps",
      "url": "https://itunes.apple.com/us/app/sarkari-result/id1051363935?ls=1&mt=8"
    },
    {
      "text": "Result",
      "url": "https://upsssc.gov.in/ResultsDire.aspx"
    },
    {
      "text": "Click Here",
      "url": "https://doc.sarkariresults.org.in/UPSSSC_13_Exam_2024_AnswerKey.pdf"
    },
    {
      "text": "Click Here",
      "url": "https://drive.google.com/file/d/1X6mCvFxmILvYwR97o5YUzTXtuPXclNbL/view"
    },
    {
      "text": "Click Here",
      "url": "https://upsssc.gov.in/upssscadmitcard/admitCard.aspx?ID=MAIN"
    },
    {
      "text": "Click Here",
      "url": "https://upsssc.gov.in/AllNotifications.aspx"
    },
    {
      "text": "Click Here",
      "url": "https://doc.sarkariresults.org.in/SarkariResult.COM_UPSSSC_Steno_Advt_NO_13_Exam_2024.pdf"
    },
    {
      "text": "Click Here",
      "url": "https://www.sarkariresult.com/upsssc/upsssc-pet-vacancy-feb24/"
    },
    {
      "text": "Sarkari Tools",
      "url": "https://sarkariresult.tools/"
    },
    {
      "text": "UPSSSC Official Website",
      "url": "https://upsssc.gov.in/"
    }
  ],
  "fetch_error": null,
  "site_name": "SarkariResult",
  "category_label": "Results",
  "scraped_date": "2026-07-22"
}