{
  "repo": "sarkariresultguthub-droid/work_baby",
  "generated_at_utc": "2026-07-19T22:37:45.139778+00:00",
  "date": "2026-07-19",
  "runs": {
    "total_runs_today": 5,
    "success": 4,
    "failed": 0,
    "other": 1,
    "run_times_utc": [
      "2026-07-19T07:18:02Z",
      "2026-07-19T11:40:58Z",
      "2026-07-19T15:33:26Z",
      "2026-07-19T19:59:09Z",
      "2026-07-19T22:36:59Z"
    ],
    "last_run_utc": "2026-07-19T22:36:59Z"
  },
  "scraped": {
    "total_files": 0,
    "by_category": {}
  }
}